<?xml version="1.0" encoding="utf-8"?>
<odoo>
    <record id="br_simples_nacional_account_invoice_line_view_form" model="ir.ui.view">
        <field name="name">br_simples_nacional.account.invoice.line.view.form</field>
        <field name="model">account.invoice.line</field>
        <field name="inherit_id" ref="br_account.view_br_account_invoice_line_form"/>
        <field name="arch" type="xml">

            <page name="issqn" position="replace"></page>
            <page name="ipi" position="replace"></page>
            <page name="pis" position="replace"></page>
            <page name="cofins" position="replace"></page>
            <page name="ii" position="replace"></page>
            <field name="icms_base_type" position="attributes">
                <attribute name="invisible">1</attribute>
            </field>
            <field name="icms_base" position="attributes">
                <attribute name="invisible">1</attribute>
            </field>
            <field name="icms_percent_reduction" position="attributes">
                <attribute name="invisible">1</attribute>
            </field>
            <field name="icms_base_other" position="attributes">
                <attribute name="invisible">1</attribute>
            </field>
            <field name="icms_percent" position="attributes">
                <attribute name="invisible">1</attribute>
            </field>
            <field name="icms_value" position="attributes">
                <attribute name="invisible">1</attribute>
            </field>
        </field>
    </record>
</odoo>
