<?xml version="1.0" encoding="utf-8"?>
<openerp>
    <data noupdate="0">

        <record id="ecd_chart_template" model="account.chart.template">
            <field name="name">Brasil - Planilha de Contas</field>
            <field name="account_root_id" ref="id_0" />
            <field name="bank_account_view_id" ref="id_1_1_1_02" />
<!--            <field name="property_account_income" ref="ECD3010101010400" />
            <field name="property_account_expense" ref="ECD3010103050000" /> -->
            <field name="property_account_receivable" ref="id_1_1_2_01_001" />
            <field name="property_account_payable" ref="id_2_1_2_01_001" />
            <field name="property_account_income_categ" ref="id_3_1_1_03_001" />
            <field name="property_account_expense_categ" ref="id_5_1_1_01_001" />
<!--            <field name="property_account_income_opening" ref="ECD3010101010400" />
            <field name="property_account_expense_opening" ref="ECD4010302040100" /> -->
            <field name="currency_id" ref="base.BRL" />
        </record>

    </data>
</openerp>
